up_consul/__init__.py
up_consul/client.py
up_consul-0.0.5.dist-info/licenses/LICENSE
up_consul-0.0.5.dist-info/METADATA
up_consul-0.0.5.dist-info/WHEEL
up_consul-0.0.5.dist-info/top_level.txt
up_consul-0.0.5.dist-info/RECORD
