Metadata-Version: 2.4
Name: up-consul
Version: 0.0.5
Summary: Limited functionality Consul Python client.
Author-email: Rowan Hatherley <rowan.hatherley@ubiquitypress.com>
Classifier: Programming Language :: Python :: 3
Classifier: License :: OSI Approved :: MIT License
Classifier: Operating System :: OS Independent
Requires-Python: >=3.10
License-File: LICENSE
Requires-Dist: requests<3.0,>=2.0
Dynamic: license-file
